MANIFEST.in
README.markdown
requirements.txt
setup.py
pin/__init__.py
pin/plugins/__init__.py
pin/plugins/pinpip.py
pinpip.egg-info/PKG-INFO
pinpip.egg-info/SOURCES.txt
pinpip.egg-info/dependency_links.txt
pinpip.egg-info/namespace_packages.txt
pinpip.egg-info/top_level.txt