Metadata-Version: 1.1
Name: pinpip
Version: 0.1rc1
Summary: Plugins providing basic pip functionality for pin.
Home-page: https://github.com/dustinlacewell/pin-pip
Author: Dustin Lacewell
Author-email: dlacewell@gmail.com
License: UNKNOWN
Platform: UNKNOWN
Provides: pinpip
